flexrilog/NAC_coloring.py
flexrilog/__init__.py
flexrilog/all.py
flexrilog/flexible_rigid_graph.py
flexrilog/graph_generator.py
flexrilog/graph_motion.py
flexrilog/motion_classification.py
flexrilog/symmetric_NAC_coloring.py
flexrilog/symmetric_flexible_rigid_graph.py
flexrilog-1.2.dist-info/COPYING
flexrilog-1.2.dist-info/LICENSE
flexrilog-1.2.dist-info/METADATA
flexrilog-1.2.dist-info/WHEEL
flexrilog-1.2.dist-info/top_level.txt
flexrilog-1.2.dist-info/RECORD
