Metadata-Version: 2.1
Name: flexrilog
Version: 1.2
Summary: FlexRiLoG - A package for investigating Flexible and Rigid Labelings of Graphs
Home-page: https://github.com/legersky/flexrilog
Author: Jan Legerský, Georg Grasegger
Author-email: jan.legersky@risc.jku.at
License: GPLv3+
Keywords: rigidity flexibility
Platform: UNKNOWN
Classifier: Development Status :: 4 - Beta
Classifier: Intended Audience :: Science/Research
Classifier: Topic :: Scientific/Engineering :: Mathematics
Classifier: License :: OSI Approved :: GNU General Public License v3 or later (GPLv3+)
Classifier: Programming Language :: Python :: 3.7
Requires-Dist: sage-package
Requires-Dist: sphinx
